{
  "@context": "/contexts/Card",
  "@id": "/cards/ALT_DUSTERCB_P_YZ_96_R1",
  "@type": "Card",
  "loreEntries": [
    {
      "@id": "/lore_entries/36FY29NBXP83C903KKNF80CB3Z",
      "@type": "LoreEntry",
      "loreEntryElements": [
        {
          "@id": "/lore_entry_elements/01KJ5PA3Y9Z4VSB6XBKHFVHWYF",
          "@type": "LoreEntryElement",
          "loreEntryElementType": {
            "@id": "/lore_entry_element_types/01GR6AENPX6HQP8G16KNV7BNA2",
            "@type": "LoreEntryElementType",
            "id": "01GR6AENPX6HQP8G16KNV7BNA2",
            "reference": "FLAVOR_TEXT",
            "subject": "Flavor Text"
          },
          "id": "01KJ5PA3Y9Z4VSB6XBKHFVHWYF",
          "text": "Espabila a los suplentes para que estén listos para saltar al campo."
        },
        {
          "@id": "/lore_entry_elements/01KJ5PA3ZNMFNP502J3A5K6592",
          "@type": "LoreEntryElement",
          "loreEntryElementType": {
            "@id": "/lore_entry_element_types/01GR6AE2ZSVVYP6SDJXN8Q5DVF",
            "@type": "LoreEntryElementType",
            "id": "01GR6AE2ZSVVYP6SDJXN8Q5DVF",
            "reference": "STORY",
            "subject": "Story"
          },
          "id": "01KJ5PA3ZNMFNP502J3A5K6592",
          "text": ""
        },
        {
          "@id": "/lore_entry_elements/01KJ5PA3YM0MZPEKH85XFVVJ3R",
          "@type": "LoreEntryElement",
          "loreEntryElementType": {
            "@id": "/lore_entry_element_types/01GR6AFCC93PF6T4EYVTXXYJY9",
            "@type": "LoreEntryElementType",
            "id": "01GR6AFCC93PF6T4EYVTXXYJY9",
            "reference": "INSPIRATION",
            "subject": "Inspiration"
          },
          "id": "01KJ5PA3YM0MZPEKH85XFVVJ3R",
          "text": ""
        },
        {
          "@id": "/lore_entry_elements/01KJ5PA3XJ363MEDNDG1P0T5P5",
          "@type": "LoreEntryElement",
          "loreEntryElementType": {
            "@id": "/lore_entry_element_types/01H19024M31D80P12EJCYX9GB0",
            "@type": "LoreEntryElementType",
            "id": "01H19024M31D80P12EJCYX9GB0",
            "reference": "NARRATOR",
            "subject": "Narrator"
          },
          "id": "01KJ5PA3XJ363MEDNDG1P0T5P5",
          "text": ""
        },
        {
          "@id": "/lore_entry_elements/01KJ5PA3XYCM22MP3JP4KE8HD2",
          "@type": "LoreEntryElement",
          "loreEntryElementType": {
            "@id": "/lore_entry_element_types/01GS7V4ZMD4F2Q0EVQ2GSSJHE2",
            "@type": "LoreEntryElementType",
            "id": "01GS7V4ZMD4F2Q0EVQ2GSSJHE2",
            "reference": "DATE",
            "subject": "Date"
          },
          "id": "01KJ5PA3XYCM22MP3JP4KE8HD2",
          "text": ""
        }
      ],
      "loreEntryType": {
        "@id": "/lore_entry_types/01HNGY4YPR0FVZVYWD8YFE0PHP",
        "@type": "LoreEntryType",
        "id": "01HNGY4YPR0FVZVYWD8YFE0PHP",
        "reference": "CHARACTER",
        "name": "Character"
      },
      "id": "36FY29NBXP83C903KKNF80CB3Z",
      "reference": "ALT_DUSTERCB_P_YZ_96_C"
    }
  ],
  "cardType": {
    "@id": "/card_types/01H19NWA92A4ERAC4ATMSZNASS",
    "@type": "CardType",
    "reference": "CHARACTER",
    "id": "01H19NWA92A4ERAC4ATMSZNASS",
    "name": "Personaje"
  },
  "cardSubTypes": [
    {
      "@type": "CardSubType",
      "@id": "/.well-known/genid/348f05ae0a4af3bd5a1c",
      "reference": "ARTIST",
      "id": "01HKAGQTJ167DYCKKGR8MCESNT",
      "name": "Artista"
    }
  ],
  "cardSet": {
    "@id": "/card_sets/DUSTERCB",
    "@type": "CardSet",
    "id": "01K60PWBQRTWXF3M650SKAQEBE",
    "reference": "DUSTERCB",
    "name": "Seeds of Unity - Collector Booster"
  },
  "rarity": {
    "@type": "Rarity",
    "@id": "/.well-known/genid/79b80cef4d4b0b61d1e2",
    "reference": "RARE",
    "id": "01GE7AC9WY6PK56RADXXD6P1T5",
    "name": "Rare"
  },
  "imagePath": "https://altered-prod-eu.s3.amazonaws.com/Art/DUSTERCB/CARDS/ALT_DUSTERCB_P_YZ_96/JPG/es_ES/1bddb9f4bd66f2c425ae753ea344fcdc.jpg",
  "assets": {
    "WEB": [
      "https://altered-prod-eu.s3.amazonaws.com/Art/DUSTERCB/CARDS/ALT_DUSTERCB_P_YZ_96/WEB_32b262f9f1432ecef3c77e467d977884",
      "https://altered-prod-eu.s3.amazonaws.com/Art/DUSTERCB/CARDS/ALT_DUSTERCB_P_YZ_96/WEB_ff107e0457c97ab9ad8a64aaf3f1ff2c",
      "https://altered-prod-eu.s3.amazonaws.com/Art/DUSTERCB/CARDS/ALT_DUSTERCB_P_YZ_96/WEB_80812f1d5ad0b21f7a7b0ff6f984fcb5"
    ]
  },
  "lowerPrice": 0,
  "qrUrlDetail": "https://qr.altered.gg/ALT_DUSTERCB_P_YZ_96_R1",
  "isOwnerless": false,
  "reference": "ALT_DUSTERCB_P_YZ_96_R1",
  "id": "01K60PWD8W298J6MWWTKX7RCJH",
  "mainFaction": {
    "@id": "/factions/YZ",
    "@type": "Faction",
    "reference": "YZ",
    "color": "#764891",
    "id": "01GE7AC9WEQKW1Y1BF8SCY7459",
    "name": "Yzmir"
  },
  "allImagePath": {
    "fr-fr": "https://altered-prod-eu.s3.amazonaws.com/Art/DUSTERCB/CARDS/ALT_DUSTERCB_P_YZ_96/JPG/fr_FR/fe9c404ebd99e9ca8c0cc4296a965c00.jpg",
    "en-us": "https://altered-prod-eu.s3.amazonaws.com/Art/DUSTERCB/CARDS/ALT_DUSTERCB_P_YZ_96/JPG/en_US/559b445afe3e1dcc1b6cacec6efce835.jpg",
    "it-it": "https://altered-prod-eu.s3.amazonaws.com/Art/DUSTERCB/CARDS/ALT_DUSTERCB_P_YZ_96/JPG/it_IT/8362fd7fd615219609dde785bac94d69.jpg",
    "es-es": "https://altered-prod-eu.s3.amazonaws.com/Art/DUSTERCB/CARDS/ALT_DUSTERCB_P_YZ_96/JPG/es_ES/1bddb9f4bd66f2c425ae753ea344fcdc.jpg",
    "de-de": "https://altered-prod-eu.s3.amazonaws.com/Art/DUSTERCB/CARDS/ALT_DUSTERCB_P_YZ_96/JPG/de_DE/9ef328e64ddeac5a203b2a70c804c6eb.jpg"
  },
  "name": "Mascota del equipo",
  "elements": {
    "MAIN_COST": "2",
    "RECALL_COST": "2",
    "OCEAN_POWER": "2",
    "FOREST_POWER": "1",
    "MOUNTAIN_POWER": "1",
    "MAIN_EFFECT": "{J} Si hay #dos o más# cartas agotadas en reserva, #hasta dos personajes objetivo# ganan 1 potenciador cada uno."
  },
  "isSuspended": false,
  "isErrated": false,
  "isBanned": false,
  "isSerialized": false,
  "isParentSerialized": false,
  "collectorNumber": "SDUCB-023-R-ES"
}