{
  "@context": "/contexts/Card",
  "@id": "/cards/ALT_FUGUE_B_YZ_146_R2",
  "@type": "Card",
  "loreEntries": [
    {
      "@id": "/lore_entries/3NC7Z9AJ0P80T8KDVGCBKFSX2Z",
      "@type": "LoreEntry",
      "loreEntryElements": [
        {
          "@id": "/lore_entry_elements/01KN46AC9QQAJ1SVT65CAZ2S95",
          "@type": "LoreEntryElement",
          "loreEntryElementType": {
            "@id": "/lore_entry_element_types/01GR6AENPX6HQP8G16KNV7BNA2",
            "@type": "LoreEntryElementType",
            "id": "01GR6AENPX6HQP8G16KNV7BNA2",
            "reference": "FLAVOR_TEXT",
            "subject": "Flavor Text"
          },
          "id": "01KN46AC9QQAJ1SVT65CAZ2S95",
          "text": ""
        },
        {
          "@id": "/lore_entry_elements/01KN46ACBY56KW7YPK919V229W",
          "@type": "LoreEntryElement",
          "loreEntryElementType": {
            "@id": "/lore_entry_element_types/01GR6AE2ZSVVYP6SDJXN8Q5DVF",
            "@type": "LoreEntryElementType",
            "id": "01GR6AE2ZSVVYP6SDJXN8Q5DVF",
            "reference": "STORY",
            "subject": "Story"
          },
          "id": "01KN46ACBY56KW7YPK919V229W",
          "text": ""
        },
        {
          "@id": "/lore_entry_elements/01KN46ACBDBY5PEG3KSP8M8600",
          "@type": "LoreEntryElement",
          "loreEntryElementType": {
            "@id": "/lore_entry_element_types/01GR6AFCC93PF6T4EYVTXXYJY9",
            "@type": "LoreEntryElementType",
            "id": "01GR6AFCC93PF6T4EYVTXXYJY9",
            "reference": "INSPIRATION",
            "subject": "Inspiration"
          },
          "id": "01KN46ACBDBY5PEG3KSP8M8600",
          "text": ""
        },
        {
          "@id": "/lore_entry_elements/01KN46AC8V0TW5P0X7RM0C4D9W",
          "@type": "LoreEntryElement",
          "loreEntryElementType": {
            "@id": "/lore_entry_element_types/01H19024M31D80P12EJCYX9GB0",
            "@type": "LoreEntryElementType",
            "id": "01H19024M31D80P12EJCYX9GB0",
            "reference": "NARRATOR",
            "subject": "Narrator"
          },
          "id": "01KN46AC8V0TW5P0X7RM0C4D9W",
          "text": ""
        },
        {
          "@id": "/lore_entry_elements/01KN46AC9AMB9708W4QMSHKMC5",
          "@type": "LoreEntryElement",
          "loreEntryElementType": {
            "@id": "/lore_entry_element_types/01GS7V4ZMD4F2Q0EVQ2GSSJHE2",
            "@type": "LoreEntryElementType",
            "id": "01GS7V4ZMD4F2Q0EVQ2GSSJHE2",
            "reference": "DATE",
            "subject": "Date"
          },
          "id": "01KN46AC9AMB9708W4QMSHKMC5",
          "text": ""
        }
      ],
      "loreEntryType": {
        "@id": "/lore_entry_types/01J20ZZP61FEFQ4613REH25WRT",
        "@type": "LoreEntryType",
        "id": "01J20ZZP61FEFQ4613REH25WRT",
        "reference": "LANDMARK_PERMANENT",
        "name": "LANDMARK_PERMANENT"
      },
      "id": "3NC7Z9AJ0P80T8KDVGCBKFSX2Z",
      "reference": "ALT_FUGUE_B_YZ_146_C"
    }
  ],
  "cardType": {
    "@id": "/card_types/01J1Q78N4S1E64PN4T7GB4T59F",
    "@type": "CardType",
    "reference": "LANDMARK_PERMANENT",
    "id": "01J1Q78N4S1E64PN4T7GB4T59F",
    "name": "Permanente hito"
  },
  "cardSubTypes": [
    {
      "@type": "CardSubType",
      "@id": "/.well-known/genid/3e6b7db6bc17c81136fd",
      "reference": "CONSTRUCTION",
      "id": "01J1SYC159ACKJS202498RAQRR",
      "name": "Construcción"
    }
  ],
  "cardSet": {
    "@id": "/card_sets/FUGUE",
    "@type": "CardSet",
    "id": "01KM5YCEK1YMWY30RHG5PV0MFY",
    "reference": "FUGUE",
    "name": "Neverending Journey"
  },
  "rarity": {
    "@type": "Rarity",
    "@id": "/.well-known/genid/2a3d8b70d3c61e9849e6",
    "reference": "RARE",
    "id": "01GE7AC9WY6PK56RADXXD6P1T5",
    "name": "Rare"
  },
  "imagePath": "https://altered-prod-eu.s3.amazonaws.com/Art/FUGUE/CARDS/ALT_FUGUE_B_YZ_146/JPG/es_ES/f37daffa26c29b68a6b3d3bf829bbb69.jpg",
  "assets": {
    "WEB": [
      "https://altered-prod-eu.s3.amazonaws.com/Art/FUGUE/CARDS/ALT_FUGUE_B_YZ_146/WEB_89578cdcb9592f893ec7a22b1c0ec492",
      "https://altered-prod-eu.s3.amazonaws.com/Art/FUGUE/CARDS/ALT_FUGUE_B_YZ_146/WEB_a1f6ad52033159d606eeaddbd5a4ac4b"
    ]
  },
  "lowerPrice": 0,
  "qrUrlDetail": "https://qr.altered.gg/ALT_FUGUE_B_YZ_146_R2",
  "isOwnerless": true,
  "reference": "ALT_FUGUE_B_YZ_146_R2",
  "id": "259QXQXK7V9MGT6YQBK4R1ND09",
  "mainFaction": {
    "@id": "/factions/OR",
    "@type": "Faction",
    "reference": "OR",
    "color": "#0f6593",
    "id": "01GE7AC9X78DXSNKNB15KCF69X",
    "name": "Ordis"
  },
  "allImagePath": {
    "fr-fr": "https://altered-prod-eu.s3.amazonaws.com/Art/FUGUE/CARDS/ALT_FUGUE_B_YZ_146/JPG/fr_FR/bb4761428c5a6ddfac220fb053a12ef6.jpg",
    "en-us": "https://altered-prod-eu.s3.amazonaws.com/Art/FUGUE/CARDS/ALT_FUGUE_B_YZ_146/JPG/en_US/74bce6f653f96159be82684f88d8c456.jpg",
    "it-it": "https://altered-prod-eu.s3.amazonaws.com/Art/FUGUE/CARDS/ALT_FUGUE_B_YZ_146/JPG/it_IT/8406d6110b3ae0a61627cb46d8edc1ff.jpg",
    "es-es": "https://altered-prod-eu.s3.amazonaws.com/Art/FUGUE/CARDS/ALT_FUGUE_B_YZ_146/JPG/es_ES/f37daffa26c29b68a6b3d3bf829bbb69.jpg",
    "de-de": "https://altered-prod-eu.s3.amazonaws.com/Art/FUGUE/CARDS/ALT_FUGUE_B_YZ_146/JPG/de_DE/8c55b4d80e05666df7b899f3042744f6.jpg"
  },
  "name": "",
  "elements": {
    "MAIN_COST": "#2#",
    "RECALL_COST": "#2#",
    "OCEAN_POWER": "",
    "FOREST_POWER": "",
    "MOUNTAIN_POWER": "",
    "MAIN_EFFECT": "{J} I gain #2 Mirage counters.#  At Noon — If you have #five or more# Mana Orbs, you may spend 1 of my Mirage counters to draw a card."
  },
  "isSuspended": false,
  "isErrated": false,
  "isBanned": false,
  "isSerialized": false,
  "isParentSerialized": false,
  "collectorNumber": "NEJ-108-F-ES"
}