{
  "@context": "/contexts/Card",
  "@id": "/cards/ALT_EOLE_B_OR_109_R2",
  "@type": "Card",
  "loreEntries": [
    {
      "@id": "/lore_entries/1YEBFHXTJF8HV8Z7VJCBY3RW3M",
      "@type": "LoreEntry",
      "loreEntryElements": [
        {
          "@id": "/lore_entry_elements/01KC94HV89Y12KEDTS1HHMAC9K",
          "@type": "LoreEntryElement",
          "loreEntryElementType": {
            "@id": "/lore_entry_element_types/01GR6AENPX6HQP8G16KNV7BNA2",
            "@type": "LoreEntryElementType",
            "id": "01GR6AENPX6HQP8G16KNV7BNA2",
            "reference": "FLAVOR_TEXT",
            "subject": "Flavor Text"
          },
          "id": "01KC94HV89Y12KEDTS1HHMAC9K",
          "text": "«Te advertí del peligro que te aguardaba». —Ayxas"
        },
        {
          "@id": "/lore_entry_elements/01KC94HV8WJWBK9443ZJYPA4D5",
          "@type": "LoreEntryElement",
          "loreEntryElementType": {
            "@id": "/lore_entry_element_types/01GR6AE2ZSVVYP6SDJXN8Q5DVF",
            "@type": "LoreEntryElementType",
            "id": "01GR6AE2ZSVVYP6SDJXN8Q5DVF",
            "reference": "STORY",
            "subject": "Story"
          },
          "id": "01KC94HV8WJWBK9443ZJYPA4D5",
          "text": "#N/A"
        },
        {
          "@id": "/lore_entry_elements/01KC94HV8KDEWZEEGA1CQ0C2K4",
          "@type": "LoreEntryElement",
          "loreEntryElementType": {
            "@id": "/lore_entry_element_types/01GR6AFCC93PF6T4EYVTXXYJY9",
            "@type": "LoreEntryElementType",
            "id": "01GR6AFCC93PF6T4EYVTXXYJY9",
            "reference": "INSPIRATION",
            "subject": "Inspiration"
          },
          "id": "01KC94HV8KDEWZEEGA1CQ0C2K4",
          "text": "#N/A"
        },
        {
          "@id": "/lore_entry_elements/01KC94HV7PF6X1T77287NBY29B",
          "@type": "LoreEntryElement",
          "loreEntryElementType": {
            "@id": "/lore_entry_element_types/01H19024M31D80P12EJCYX9GB0",
            "@type": "LoreEntryElementType",
            "id": "01H19024M31D80P12EJCYX9GB0",
            "reference": "NARRATOR",
            "subject": "Narrator"
          },
          "id": "01KC94HV7PF6X1T77287NBY29B",
          "text": "#N/A"
        },
        {
          "@id": "/lore_entry_elements/01KC94HV80DYNVY9V3KSRJG4WR",
          "@type": "LoreEntryElement",
          "loreEntryElementType": {
            "@id": "/lore_entry_element_types/01GS7V4ZMD4F2Q0EVQ2GSSJHE2",
            "@type": "LoreEntryElementType",
            "id": "01GS7V4ZMD4F2Q0EVQ2GSSJHE2",
            "reference": "DATE",
            "subject": "Date"
          },
          "id": "01KC94HV80DYNVY9V3KSRJG4WR",
          "text": "#N/A"
        }
      ],
      "loreEntryType": {
        "@id": "/lore_entry_types/01HNGY4YPR0FVZVYWD8YFE0PHP",
        "@type": "LoreEntryType",
        "id": "01HNGY4YPR0FVZVYWD8YFE0PHP",
        "reference": "CHARACTER",
        "name": "Character"
      },
      "id": "1YEBFHXTJF8HV8Z7VJCBY3RW3M",
      "reference": "ALT_EOLE_B_OR_109_C"
    }
  ],
  "cardType": {
    "@id": "/card_types/01H19NWA92A4ERAC4ATMSZNASS",
    "@type": "CardType",
    "reference": "CHARACTER",
    "id": "01H19NWA92A4ERAC4ATMSZNASS",
    "name": "Personaje"
  },
  "cardSubTypes": [
    {
      "@type": "CardSubType",
      "@id": "/.well-known/genid/3f476c1748dc39b3156e",
      "reference": "NOBLE",
      "id": "01HKAGVEV163KJH0BWMZ6WR7E9",
      "name": "Noble"
    },
    {
      "@type": "CardSubType",
      "@id": "/.well-known/genid/eade02d3d11bf9356b64",
      "reference": "ROGUE",
      "id": "01JZ2K0A1NZSGT69DP1WS2917B",
      "name": "Pícaro"
    }
  ],
  "cardSet": {
    "@id": "/card_sets/EOLE",
    "@type": "CardSet",
    "id": "01K9YWHXF2T6GJJDWAK333TJGV",
    "reference": "EOLE",
    "name": "Roots of Corruption"
  },
  "rarity": {
    "@type": "Rarity",
    "@id": "/.well-known/genid/c6dcb7eb100ab2b9079f",
    "reference": "RARE",
    "id": "01GE7AC9WY6PK56RADXXD6P1T5",
    "name": "Rare"
  },
  "imagePath": "https://altered-prod-eu.s3.amazonaws.com/Art/EOLE/CARDS/ALT_EOLE_B_OR_109/JPG/es_ES/f69df738c7d07c78ccac3e538b3c587c.jpg",
  "assets": {
    "WEB": [
      "https://altered-prod-eu.s3.amazonaws.com/Art/EOLE/CARDS/ALT_EOLE_B_OR_109/WEB_a137bdb22f5c096d7a5f5197f65c4917",
      "https://altered-prod-eu.s3.amazonaws.com/Art/EOLE/CARDS/ALT_EOLE_B_OR_109/WEB_326412f11cdc44e5c2dee705762cc2f3",
      "https://altered-prod-eu.s3.amazonaws.com/Art/EOLE/CARDS/ALT_EOLE_B_OR_109/WEB_51e7050b278ba919ce6dd069c1a8c61c"
    ]
  },
  "lowerPrice": 0,
  "qrUrlDetail": "https://qr.altered.gg/ALT_EOLE_B_OR_109_R2",
  "isOwnerless": true,
  "reference": "ALT_EOLE_B_OR_109_R2",
  "id": "01K9YWHY9THTRAX12Z5PHQM6M0",
  "mainFaction": {
    "@id": "/factions/MU",
    "@type": "Faction",
    "reference": "MU",
    "color": "#3d6b42",
    "id": "01GE7AC9X2BNM40TTAYAEFSZSJ",
    "name": "Muna"
  },
  "allImagePath": {
    "fr-fr": "https://altered-prod-eu.s3.amazonaws.com/Art/EOLE/CARDS/ALT_EOLE_B_OR_109/JPG/fr_FR/2e2927fb2a3342e67ecacf53ce0c8ebf.jpg",
    "en-us": "https://altered-prod-eu.s3.amazonaws.com/Art/EOLE/CARDS/ALT_EOLE_B_OR_109/JPG/en_US/40a5ff09b9a577bee2a16c6a04f093e8.jpg",
    "it-it": "https://altered-prod-eu.s3.amazonaws.com/Art/EOLE/CARDS/ALT_EOLE_B_OR_109/JPG/it_IT/e6ce7611709ef5522177c756725c3775.jpg",
    "es-es": "https://altered-prod-eu.s3.amazonaws.com/Art/EOLE/CARDS/ALT_EOLE_B_OR_109/JPG/es_ES/f69df738c7d07c78ccac3e538b3c587c.jpg",
    "de-de": "https://altered-prod-eu.s3.amazonaws.com/Art/EOLE/CARDS/ALT_EOLE_B_OR_109/JPG/de_DE/c3c947956bff8ace65f8edf483cc69b6.jpg"
  },
  "name": "Ayxas, tirano arrepentido",
  "elements": {
    "MAIN_COST": "#2#",
    "RECALL_COST": "#2#",
    "OCEAN_POWER": "#2#",
    "FOREST_POWER": "#2#",
    "MOUNTAIN_POWER": "#2#",
    "MAIN_EFFECT": "{H} Puedes crear una ficha de #animal [Lanudo 1/1/1]# en la expedición de un oponente para [Sabotear]."
  },
  "isSuspended": false,
  "isErrated": false,
  "isBanned": false,
  "isSerialized": false,
  "isParentSerialized": false,
  "collectorNumber": "ROC-083-F-ES"
}