{
  "@context": "/contexts/PublicCard",
  "@id": "/public/cards/ALT_EOLEOP_P_LY_111_C",
  "@type": "PublicCard",
  "id": "01KGH7QTMHXS7F2QJMVJ5RN29X",
  "reference": "ALT_EOLEOP_P_LY_111_C",
  "cardType": {
    "@type": "CardTypeDTO",
    "@id": "/.well-known/genid/ee991ca47c1ed8de3e55",
    "id": "01H19NWA92A4ERAC4ATMSZNASS",
    "reference": "CHARACTER",
    "name": "Personnage",
    "sequence": 3
  },
  "cardSet": {
    "@type": "CardSetDTO",
    "@id": "/.well-known/genid/adb669b8c22c47a9a48f",
    "id": "01KGH7QT3S6RRZK2S0BNBVNH3K",
    "reference": "EOLEOP",
    "name": "Les Racines de la Corruption - Jeu Organisé",
    "description": null,
    "code": "ROCOP",
    "isActive": true,
    "isReward": true
  },
  "cardSubTypes": [
    {
      "@type": "CardSubTypeDTO",
      "@id": "/.well-known/genid/0d38fc2b26722fae6160",
      "id": "01HKAGPAJFS4YDQVKY6AB16614",
      "reference": "DEITY",
      "name": "Divinité"
    }
  ],
  "elements": {
    "MAIN_COST": "3",
    "RECALL_COST": "3",
    "MOUNTAIN_POWER": "3",
    "OCEAN_POWER": "3",
    "FOREST_POWER": "2",
    "MAIN_EFFECT": "",
    "ECHO_EFFECT": "{D} : Le prochain Personnage de Coût de Base {3} ou moins que vous jouez ce tour-ci gagne [[Ancré]]."
  },
  "rarity": {
    "@type": "RarityDTO",
    "@id": "/.well-known/genid/b318495dc390c6dc4963",
    "id": "01GE7AC9WEQKW1Y1BF8SCY745A",
    "reference": "COMMON",
    "name": "Commun",
    "sequence": 0
  },
  "imagePath": "https://altered-prod-eu.s3.amazonaws.com/Art/EOLEOP/CARDS/ALT_EOLEOP_P_LY_111/JPG/fr_FR/ffda857f3549846c9cfdbf1504e94665.jpg",
  "assets": {
    "WEB": [
      "https://altered-prod-eu.s3.amazonaws.com/Art/EOLEOP/CARDS/ALT_EOLEOP_P_LY_111/WEB_ed459c352ec44b6b9d45e8bd1bf63dd6",
      "https://altered-prod-eu.s3.amazonaws.com/Art/EOLEOP/CARDS/ALT_EOLEOP_P_LY_111/WEB_2429a893be767a7a5daec141d3bc4c3a",
      "https://altered-prod-eu.s3.amazonaws.com/Art/EOLEOP/CARDS/ALT_EOLEOP_P_LY_111/WEB_664ea17f08b49eaa695d30ddf152bf6f"
    ]
  },
  "mainFaction": {
    "@type": "FactionDTO",
    "@id": "/.well-known/genid/97f167821bb1b4e049cb",
    "id": "01GE7AC9XGB6JE2V63WXWN4FB3",
    "reference": "LY",
    "name": "Lyra",
    "color": "#cf4171"
  },
  "name": "Bastet",
  "isSuspended": false,
  "isSerialized": false,
  "isParentSerialized": false,
  "isErrated": false,
  "isBanned": false,
  "isOwnerless": false,
  "inSale": 0,
  "lowerPrice": 0,
  "lowerOfferId": "",
  "isExclusive": true,
  "collectorNumber": "ALT_EOLEOP_P_LY_111_C-FR"
}