{
  "@context": "/contexts/PublicCard",
  "@id": "/public/cards/ALT_EOLEOP_A_LY_111_C",
  "@type": "PublicCard",
  "id": "01KGH9QGKRCQW83A8AGQT150MJ",
  "reference": "ALT_EOLEOP_A_LY_111_C",
  "cardType": {
    "@type": "CardTypeDTO",
    "@id": "/.well-known/genid/94b5d1f51ef83bb2fdde",
    "id": "01H19NWA92A4ERAC4ATMSZNASS",
    "reference": "CHARACTER",
    "name": "Personaggio",
    "sequence": 3
  },
  "cardSet": {
    "@type": "CardSetDTO",
    "@id": "/.well-known/genid/c3672ac1b92032cdbe01",
    "id": "01KGH7QT3S6RRZK2S0BNBVNH3K",
    "reference": "EOLEOP",
    "name": "Roots of Corruption - Organized Play",
    "description": null,
    "code": "ROCOP",
    "isActive": true,
    "isReward": true
  },
  "cardSubTypes": [
    {
      "@type": "CardSubTypeDTO",
      "@id": "/.well-known/genid/34cbd3311a99d6f4d41e",
      "id": "01HKAGPAJFS4YDQVKY6AB16614",
      "reference": "DEITY",
      "name": "Divinità"
    }
  ],
  "elements": {
    "MAIN_COST": "3",
    "RECALL_COST": "3",
    "MOUNTAIN_POWER": "3",
    "OCEAN_POWER": "3",
    "FOREST_POWER": "2",
    "MAIN_EFFECT": "",
    "ECHO_EFFECT": "{D}: il prossimo personaggio con costo base pari o inferiore a {3} che giochi in questo turno ottiene [[Ancorato]]."
  },
  "rarity": {
    "@type": "RarityDTO",
    "@id": "/.well-known/genid/a2aaa1c8dba4f5f35937",
    "id": "01GE7AC9WEQKW1Y1BF8SCY745A",
    "reference": "COMMON",
    "name": "Common",
    "sequence": 0
  },
  "imagePath": "https://altered-prod-eu.s3.amazonaws.com/Art/EOLEOP/CARDS/ALT_EOLEOP_A_LY_111/JPG/it_IT/c257f0dd128b23581fed68212e248675.jpg",
  "assets": [],
  "mainFaction": {
    "@type": "FactionDTO",
    "@id": "/.well-known/genid/247de131065d52703da7",
    "id": "01GE7AC9XGB6JE2V63WXWN4FB3",
    "reference": "LY",
    "name": "Lyra",
    "color": "#cf4171"
  },
  "name": "Bastet",
  "isSuspended": false,
  "isSerialized": false,
  "isParentSerialized": false,
  "isErrated": false,
  "isBanned": false,
  "isOwnerless": false,
  "inSale": 0,
  "lowerPrice": 0,
  "lowerOfferId": "",
  "isExclusive": true,
  "collectorNumber": "ALT_EOLEOP_A_LY_111_C-IT"
}