{
  "@context": "/contexts/Card",
  "@id": "/cards/ALT_DUSTERTOP_P_OR_08_R1",
  "@type": "Card",
  "loreEntries": [
    {
      "@id": "/lore_entries/1G0A56CA9M9T39BJWCM21S9X7H",
      "@type": "LoreEntry",
      "loreEntryElements": [
        {
          "@id": "/lore_entry_elements/01K5GZMJ3D0KM5VP074RZ92M4M",
          "@type": "LoreEntryElement",
          "loreEntryElementType": {
            "@id": "/lore_entry_element_types/01GR6AENPX6HQP8G16KNV7BNA2",
            "@type": "LoreEntryElementType",
            "id": "01GR6AENPX6HQP8G16KNV7BNA2",
            "reference": "FLAVOR_TEXT",
            "subject": "Flavor Text"
          },
          "id": "01K5GZMJ3D0KM5VP074RZ92M4M",
          "text": "« Votre document a expiré. Pour toute réclamation, prenez rendez-vous avec l'Archiviste. »"
        },
        {
          "@id": "/lore_entry_elements/01K5GZMJ3R3TQ7W9QCZQD63KNX",
          "@type": "LoreEntryElement",
          "loreEntryElementType": {
            "@id": "/lore_entry_element_types/01GR6AE2ZSVVYP6SDJXN8Q5DVF",
            "@type": "LoreEntryElementType",
            "id": "01GR6AE2ZSVVYP6SDJXN8Q5DVF",
            "reference": "STORY",
            "subject": "Histoire"
          },
          "id": "01K5GZMJ3R3TQ7W9QCZQD63KNX",
          "text": "La Légat me toise alors que je lui soumets en toute discrétion le projet de lancement de l'Effort de Redécouverte. Elle hausse les sourcils avec un air agacé, et entreprend de le lire, avec pour claire consigne d'en souligner toutes les failles. Bien entendu, je suis passé par des réseaux officiels ; il n'y a donc aucune raison qu'elle suspecte une quelconque tricherie. Elle doit tout juste penser que mon objectif, en tant qu'opposant public d'Avkan, est de dénicher de quoi discréditer l'édit, de quoi mettre des bâtons dans les roues de mon rival. Bien sûr, elle ne le fait pas de bon cœur, et elle me le signifie par son attitude pincée et revêche. Pour autant, la démarche s'ancre dans un procédé on ne peut plus démocratique. Même si cela va à l'encontre de ses propres convictions, elle ne peut s'y opposer et elle le sait très bien.\n\nFidèle à mon personnage, je lui intime de se presser, claquant la langue avec désobligeance pour lui faire part de mon irritation et de mon impatience. Elle me fusille du regard, mais continue d'éplucher le document sans mot dire. Plus elle me détestera, plus elle sera inconsciemment réceptive aux demandes des partisans d'Avkan le moment venu. Elle repose le document annoté et le glisse sur la table dans ma direction. Je le saisis sans même un remerciement, me fendant d'un soupir exaspéré. Je la sens fulminer en silence tandis que je lis ses addenda. Comme on pouvait s'y attendre, le projet présentait des problématiques de financement, et les coupes budgétaires nécessaires pour financer l'entreprise allaient certainement créer la grogne. Il y avait aussi une question de temporalité, et surtout de continuité. En l'état, le mandat du Basileus ne suffirait pas à la concrétiser. Et surtout... hmm, il fallait que j'apporte ce document à Avkan pour qu'il prenne conscience de certaines implications légales."
        },
        {
          "@id": "/lore_entry_elements/01K5GZMJ3JAH4V4GEE6CJVRQ74",
          "@type": "LoreEntryElement",
          "loreEntryElementType": {
            "@id": "/lore_entry_element_types/01GR6AFCC93PF6T4EYVTXXYJY9",
            "@type": "LoreEntryElementType",
            "id": "01GR6AFCC93PF6T4EYVTXXYJY9",
            "reference": "INSPIRATION",
            "subject": "Inspiration"
          },
          "id": "01K5GZMJ3JAH4V4GEE6CJVRQ74",
          "text": ""
        },
        {
          "@id": "/lore_entry_elements/01K5GZMJ32Z4GBGRA6QB2FG7SE",
          "@type": "LoreEntryElement",
          "loreEntryElementType": {
            "@id": "/lore_entry_element_types/01H19024M31D80P12EJCYX9GB0",
            "@type": "LoreEntryElementType",
            "id": "01H19024M31D80P12EJCYX9GB0",
            "reference": "NARRATOR",
            "subject": "Narré par"
          },
          "id": "01K5GZMJ32Z4GBGRA6QB2FG7SE",
          "text": "Waru"
        },
        {
          "@id": "/lore_entry_elements/01K5GZMJ3869CZC3WYP607X04Q",
          "@type": "LoreEntryElement",
          "loreEntryElementType": {
            "@id": "/lore_entry_element_types/01GS7V4ZMD4F2Q0EVQ2GSSJHE2",
            "@type": "LoreEntryElementType",
            "id": "01GS7V4ZMD4F2Q0EVQ2GSSJHE2",
            "reference": "DATE",
            "subject": "Date"
          },
          "id": "01K5GZMJ3869CZC3WYP607X04Q",
          "text": "363 AC"
        }
      ],
      "loreEntryType": {
        "@id": "/lore_entry_types/01HNGY4YPR0FVZVYWD8YFE0PHP",
        "@type": "LoreEntryType",
        "id": "01HNGY4YPR0FVZVYWD8YFE0PHP",
        "reference": "CHARACTER",
        "name": "Character"
      },
      "id": "1G0A56CA9M9T39BJWCM21S9X7H",
      "reference": "ALT_DUSTERTOP_P_OR_08_C"
    }
  ],
  "cardType": {
    "@id": "/card_types/01H19NWA92A4ERAC4ATMSZNASS",
    "@type": "CardType",
    "reference": "CHARACTER",
    "id": "01H19NWA92A4ERAC4ATMSZNASS",
    "name": "Personnage"
  },
  "cardSubTypes": [
    {
      "@type": "CardSubType",
      "@id": "/.well-known/genid/a3c8dd55c8908a7dac50",
      "reference": "BUREAUCRAT",
      "id": "01HKAGVBV23NSWD6EXJXSKK3F8",
      "name": "Bureaucrate"
    }
  ],
  "cardSet": {
    "@id": "/card_sets/DUSTERTOP",
    "@type": "CardSet",
    "id": "01K571ZHWV0VPWZX736JAJEGAP",
    "reference": "DUSTERTOP",
    "name": "Les Graines de l'Unité - Box Topper"
  },
  "rarity": {
    "@type": "Rarity",
    "@id": "/.well-known/genid/b9b1b186faf916709f09",
    "reference": "RARE",
    "id": "01GE7AC9WY6PK56RADXXD6P1T5",
    "name": "Rare"
  },
  "imagePath": "https://altered-prod-eu.s3.amazonaws.com/Art/DUSTERTOP/CARDS/ALT_DUSTERTOP_P_OR_08/JPG/fr_FR/3d0976f89f2aa3772696fad86d9970cf.jpg",
  "assets": {
    "WEB": [
      "https://altered-prod-eu.s3.amazonaws.com/Art/DUSTERTOP/CARDS/ALT_DUSTERTOP_P_OR_08/WEB_f1c06344dc0a6d18bd93af473400d170",
      "https://altered-prod-eu.s3.amazonaws.com/Art/DUSTERTOP/CARDS/ALT_DUSTERTOP_P_OR_08/WEB_41c8bd1bcf665a9d433e5cc9e1e493e1",
      "https://altered-prod-eu.s3.amazonaws.com/Art/DUSTERTOP/CARDS/ALT_DUSTERTOP_P_OR_08/WEB_763f85f01b107a4d9e1b9b23145780fb"
    ]
  },
  "lowerPrice": 0,
  "qrUrlDetail": "https://qr.altered.gg/ALT_DUSTERTOP_P_OR_08_R1",
  "isOwnerless": false,
  "reference": "ALT_DUSTERTOP_P_OR_08_R1",
  "id": "01K57206G666C8711FXG69685S",
  "mainFaction": {
    "@id": "/factions/OR",
    "@type": "Faction",
    "reference": "OR",
    "color": "#0f6593",
    "id": "01GE7AC9X78DXSNKNB15KCF69X",
    "name": "Ordis"
  },
  "allImagePath": {
    "fr-fr": "https://altered-prod-eu.s3.amazonaws.com/Art/DUSTERTOP/CARDS/ALT_DUSTERTOP_P_OR_08/JPG/fr_FR/3d0976f89f2aa3772696fad86d9970cf.jpg",
    "en-us": "https://altered-prod-eu.s3.amazonaws.com/Art/DUSTERTOP/CARDS/ALT_DUSTERTOP_P_OR_08/JPG/en_US/3f74cf5868138dfe5ae1be1bfe0ccddc.jpg",
    "it-it": "https://altered-prod-eu.s3.amazonaws.com/Art/DUSTERTOP/CARDS/ALT_DUSTERTOP_P_OR_08/JPG/it_IT/ae7d10d20bb45ae452f5587153d98488.jpg",
    "es-es": "https://altered-prod-eu.s3.amazonaws.com/Art/DUSTERTOP/CARDS/ALT_DUSTERTOP_P_OR_08/JPG/es_ES/cf58d449a318b4c7adb1be5f5ce71f66.jpg",
    "de-de": "https://altered-prod-eu.s3.amazonaws.com/Art/DUSTERTOP/CARDS/ALT_DUSTERTOP_P_OR_08/JPG/de_DE/78b5b9cf02608fc29058c66760408b7a.jpg"
  },
  "name": "Légat du Monolithe",
  "elements": {
    "MAIN_COST": "2",
    "RECALL_COST": "2",
    "OCEAN_POWER": "2",
    "FOREST_POWER": "2",
    "MOUNTAIN_POWER": "#2#",
    "MAIN_EFFECT": "Lorsque mon Expédition n'avance pas pendant le Crépuscule — [Sabotez] après le Repos.",
    "ECHO_EFFECT": "#{D} : Create an [1/1/1 Recrue Ordis] Soldier token in target Expedition.# (Discard me from Reserve to do this.)"
  },
  "isSuspended": false,
  "isErrated": false,
  "isBanned": false,
  "isSerialized": false,
  "isParentSerialized": false,
  "collectorNumber": "SDUTOP-010-R-FR"
}