{
  "@context": "/contexts/Card",
  "@id": "/cards/ALT_EOLE_B_YZ_110_C",
  "@type": "Card",
  "loreEntries": [
    {
      "@id": "/lore_entries/2ENWEMWEKV9ZFAW4ZC0TVMAZ3K",
      "@type": "LoreEntry",
      "loreEntryElements": [
        {
          "@id": "/lore_entry_elements/01KC94HY0D0RD49D4YEDXFP8F5",
          "@type": "LoreEntryElement",
          "loreEntryElementType": {
            "@id": "/lore_entry_element_types/01GR6AENPX6HQP8G16KNV7BNA2",
            "@type": "LoreEntryElementType",
            "id": "01GR6AENPX6HQP8G16KNV7BNA2",
            "reference": "FLAVOR_TEXT",
            "subject": "Flavor Text"
          },
          "id": "01KC94HY0D0RD49D4YEDXFP8F5",
          "text": "Ses pinces épinglent le tissu de la réalité."
        },
        {
          "@id": "/lore_entry_elements/01KC94HY2DW0WDXSEZTMVXKEPT",
          "@type": "LoreEntryElement",
          "loreEntryElementType": {
            "@id": "/lore_entry_element_types/01GR6AE2ZSVVYP6SDJXN8Q5DVF",
            "@type": "LoreEntryElementType",
            "id": "01GR6AE2ZSVVYP6SDJXN8Q5DVF",
            "reference": "STORY",
            "subject": "Histoire"
          },
          "id": "01KC94HY2DW0WDXSEZTMVXKEPT",
          "text": "#N/A"
        },
        {
          "@id": "/lore_entry_elements/01KC94HY1T7TVT9D4RKDDK6S1E",
          "@type": "LoreEntryElement",
          "loreEntryElementType": {
            "@id": "/lore_entry_element_types/01GR6AFCC93PF6T4EYVTXXYJY9",
            "@type": "LoreEntryElementType",
            "id": "01GR6AFCC93PF6T4EYVTXXYJY9",
            "reference": "INSPIRATION",
            "subject": "Inspiration"
          },
          "id": "01KC94HY1T7TVT9D4RKDDK6S1E",
          "text": "#N/A"
        },
        {
          "@id": "/lore_entry_elements/01KC94HXZPGB0QTYANSMSY9V3V",
          "@type": "LoreEntryElement",
          "loreEntryElementType": {
            "@id": "/lore_entry_element_types/01H19024M31D80P12EJCYX9GB0",
            "@type": "LoreEntryElementType",
            "id": "01H19024M31D80P12EJCYX9GB0",
            "reference": "NARRATOR",
            "subject": "Narré par"
          },
          "id": "01KC94HXZPGB0QTYANSMSY9V3V",
          "text": "#N/A"
        },
        {
          "@id": "/lore_entry_elements/01KC94HY01YDHZ9V0PEKD4PRPB",
          "@type": "LoreEntryElement",
          "loreEntryElementType": {
            "@id": "/lore_entry_element_types/01GS7V4ZMD4F2Q0EVQ2GSSJHE2",
            "@type": "LoreEntryElementType",
            "id": "01GS7V4ZMD4F2Q0EVQ2GSSJHE2",
            "reference": "DATE",
            "subject": "Date"
          },
          "id": "01KC94HY01YDHZ9V0PEKD4PRPB",
          "text": "#N/A"
        }
      ],
      "loreEntryType": {
        "@id": "/lore_entry_types/01HNGY4YPR0FVZVYWD8YFE0PHP",
        "@type": "LoreEntryType",
        "id": "01HNGY4YPR0FVZVYWD8YFE0PHP",
        "reference": "CHARACTER",
        "name": "Character"
      },
      "id": "2ENWEMWEKV9ZFAW4ZC0TVMAZ3K",
      "reference": "ALT_EOLE_B_YZ_110_C"
    }
  ],
  "cardType": {
    "@id": "/card_types/01H19NWA92A4ERAC4ATMSZNASS",
    "@type": "CardType",
    "reference": "CHARACTER",
    "id": "01H19NWA92A4ERAC4ATMSZNASS",
    "name": "Personnage"
  },
  "cardSubTypes": [
    {
      "@type": "CardSubType",
      "@id": "/.well-known/genid/554afda69ff2e6fd7e99",
      "reference": "ANIMAL",
      "id": "01HKAGQS36Z3DP166MZW8KRAEK",
      "name": "Animal"
    }
  ],
  "cardSet": {
    "@id": "/card_sets/EOLE",
    "@type": "CardSet",
    "id": "01K9YWHXF2T6GJJDWAK333TJGV",
    "reference": "EOLE",
    "name": "Les Racines de la Corruption"
  },
  "rarity": {
    "@type": "Rarity",
    "@id": "/.well-known/genid/0537cb199ce5417c0ee2",
    "reference": "COMMON",
    "id": "01GE7AC9WEQKW1Y1BF8SCY745A",
    "name": "Commun"
  },
  "imagePath": "https://altered-prod-eu.s3.amazonaws.com/Art/EOLE/CARDS/ALT_EOLE_B_YZ_110/JPG/fr_FR/e34aad1c49d34e5dc3de153ff0cba95a.jpg",
  "assets": {
    "WEB": [
      "https://altered-prod-eu.s3.amazonaws.com/Art/EOLE/CARDS/ALT_EOLE_B_YZ_110/WEB_813be7f3f5d2ea4501435ded3ccf48bc",
      "https://altered-prod-eu.s3.amazonaws.com/Art/EOLE/CARDS/ALT_EOLE_B_YZ_110/WEB_5fa1fc92f13e0e64d8b1d060e182f270",
      "https://altered-prod-eu.s3.amazonaws.com/Art/EOLE/CARDS/ALT_EOLE_B_YZ_110/WEB_f13928addbb97499d4fee7841fd13609"
    ]
  },
  "lowerPrice": 0,
  "qrUrlDetail": "https://qr.altered.gg/ALT_EOLE_B_YZ_110_C",
  "isOwnerless": true,
  "reference": "ALT_EOLE_B_YZ_110_C",
  "id": "01K9YWHYA3B8H033BAGTRPZRNR",
  "mainFaction": {
    "@id": "/factions/YZ",
    "@type": "Faction",
    "reference": "YZ",
    "color": "#764891",
    "id": "01GE7AC9WEQKW1Y1BF8SCY7459",
    "name": "Yzmir"
  },
  "allImagePath": {
    "fr-fr": "https://altered-prod-eu.s3.amazonaws.com/Art/EOLE/CARDS/ALT_EOLE_B_YZ_110/JPG/fr_FR/e34aad1c49d34e5dc3de153ff0cba95a.jpg",
    "en-us": "https://altered-prod-eu.s3.amazonaws.com/Art/EOLE/CARDS/ALT_EOLE_B_YZ_110/JPG/en_US/c7e20741eb97835f6ee277f2c65fe0f5.jpg",
    "it-it": "https://altered-prod-eu.s3.amazonaws.com/Art/EOLE/CARDS/ALT_EOLE_B_YZ_110/JPG/it_IT/8b6cdf61ed6d8d7e91d7b576904cac03.jpg",
    "es-es": "https://altered-prod-eu.s3.amazonaws.com/Art/EOLE/CARDS/ALT_EOLE_B_YZ_110/JPG/es_ES/192248f110a642e4e01ac271cdf2d036.jpg",
    "de-de": "https://altered-prod-eu.s3.amazonaws.com/Art/EOLE/CARDS/ALT_EOLE_B_YZ_110/JPG/de_DE/2575d56131f16a9d29b988e58c0533ca.jpg"
  },
  "name": "Crabe en Mue",
  "elements": {
    "MAIN_COST": "3",
    "RECALL_COST": "3",
    "OCEAN_POWER": "4",
    "FOREST_POWER": "2",
    "MOUNTAIN_POWER": "2",
    "MAIN_EFFECT": "{H} Piochez une carte, puis défaussez une carte de votre main."
  },
  "isSuspended": false,
  "isErrated": false,
  "isBanned": false,
  "isSerialized": false,
  "isParentSerialized": false,
  "collectorNumber": "ROC-103-C-FR"
}