{
  "@context": "/contexts/Card",
  "@id": "/cards/ALT_EOLECB_A_AX_108_R1",
  "@type": "Card",
  "loreEntries": [
    {
      "@id": "/lore_entries/71GMKJDYKK82PB7AE5P56E7QXX",
      "@type": "LoreEntry",
      "loreEntryElements": [
        {
          "@id": "/lore_entry_elements/01KHBKDK67VTD4YZ2ZXR8TBQMR",
          "@type": "LoreEntryElement",
          "loreEntryElementType": {
            "@id": "/lore_entry_element_types/01GR6AENPX6HQP8G16KNV7BNA2",
            "@type": "LoreEntryElementType",
            "id": "01GR6AENPX6HQP8G16KNV7BNA2",
            "reference": "FLAVOR_TEXT",
            "subject": "Flavor Text"
          },
          "id": "01KHBKDK67VTD4YZ2ZXR8TBQMR",
          "text": "Manche Erinnerungen werden immer bitter schmecken."
        },
        {
          "@id": "/lore_entry_elements/01KHBKDK6JF557GBGVJFD6F6AK",
          "@type": "LoreEntryElement",
          "loreEntryElementType": {
            "@id": "/lore_entry_element_types/01GR6AE2ZSVVYP6SDJXN8Q5DVF",
            "@type": "LoreEntryElementType",
            "id": "01GR6AE2ZSVVYP6SDJXN8Q5DVF",
            "reference": "STORY",
            "subject": "Story"
          },
          "id": "01KHBKDK6JF557GBGVJFD6F6AK",
          "text": ""
        },
        {
          "@id": "/lore_entry_elements/01KHBKDK6CXGKM8C1NBZ5TAQKC",
          "@type": "LoreEntryElement",
          "loreEntryElementType": {
            "@id": "/lore_entry_element_types/01GR6AFCC93PF6T4EYVTXXYJY9",
            "@type": "LoreEntryElementType",
            "id": "01GR6AFCC93PF6T4EYVTXXYJY9",
            "reference": "INSPIRATION",
            "subject": "Inspiration"
          },
          "id": "01KHBKDK6CXGKM8C1NBZ5TAQKC",
          "text": ""
        },
        {
          "@id": "/lore_entry_elements/01KHBKDK5TZQWTXF3ADNV6H5Q6",
          "@type": "LoreEntryElement",
          "loreEntryElementType": {
            "@id": "/lore_entry_element_types/01H19024M31D80P12EJCYX9GB0",
            "@type": "LoreEntryElementType",
            "id": "01H19024M31D80P12EJCYX9GB0",
            "reference": "NARRATOR",
            "subject": "Narrator"
          },
          "id": "01KHBKDK5TZQWTXF3ADNV6H5Q6",
          "text": ""
        },
        {
          "@id": "/lore_entry_elements/01KHBKDK610M7DD9J50TJ3H0MS",
          "@type": "LoreEntryElement",
          "loreEntryElementType": {
            "@id": "/lore_entry_element_types/01GS7V4ZMD4F2Q0EVQ2GSSJHE2",
            "@type": "LoreEntryElementType",
            "id": "01GS7V4ZMD4F2Q0EVQ2GSSJHE2",
            "reference": "DATE",
            "subject": "Date"
          },
          "id": "01KHBKDK610M7DD9J50TJ3H0MS",
          "text": ""
        }
      ],
      "loreEntryType": {
        "@id": "/lore_entry_types/01HNGY4YPR0FVZVYWD8YFE0PHP",
        "@type": "LoreEntryType",
        "id": "01HNGY4YPR0FVZVYWD8YFE0PHP",
        "reference": "CHARACTER",
        "name": "Character"
      },
      "id": "71GMKJDYKK82PB7AE5P56E7QXX",
      "reference": "ALT_EOLECB_A_AX_108_C"
    }
  ],
  "cardType": {
    "@id": "/card_types/01H19NWA92A4ERAC4ATMSZNASS",
    "@type": "CardType",
    "reference": "CHARACTER",
    "id": "01H19NWA92A4ERAC4ATMSZNASS",
    "name": "Charakter"
  },
  "cardSubTypes": [
    {
      "@type": "CardSubType",
      "@id": "/.well-known/genid/e8de4b26426cf413c5fa",
      "reference": "ADVENTURER",
      "id": "01HKAGPC92CGHANVSRSC8R8ES6",
      "name": "Abenteurer"
    },
    {
      "@type": "CardSubType",
      "@id": "/.well-known/genid/1aebdf7b72e26d934af4",
      "reference": "CORRUPTION",
      "id": "01KA0YFDBT5GF5YYW6RP9VJ0GB",
      "name": "Verfall"
    }
  ],
  "cardSet": {
    "@id": "/card_sets/EOLECB",
    "@type": "CardSet",
    "id": "01KH6E44GRCVN6CHNG9FY4KNXQ",
    "reference": "EOLECB",
    "name": "Roots of Corruption - Collector Booster"
  },
  "rarity": {
    "@type": "Rarity",
    "@id": "/.well-known/genid/8ecd0d4a0bad7535d438",
    "reference": "RARE",
    "id": "01GE7AC9WY6PK56RADXXD6P1T5",
    "name": "Rare"
  },
  "imagePath": "https://altered-prod-eu.s3.amazonaws.com/Art/EOLECB/CARDS/ALT_EOLECB_A_AX_108/JPG/de_DE/d33aba9dfed211c8a7c84ae80d178fbc.jpg",
  "assets": {
    "WEB": [
      "https://altered-prod-eu.s3.amazonaws.com/Art/EOLECB/CARDS/ALT_EOLECB_A_AX_108/WEB_77862bf7cba8f1d263ecca435a27300b",
      "https://altered-prod-eu.s3.amazonaws.com/Art/EOLECB/CARDS/ALT_EOLECB_A_AX_108/WEB_e85677da5f404002807c3e8fdac13dfc",
      "https://altered-prod-eu.s3.amazonaws.com/Art/EOLECB/CARDS/ALT_EOLECB_A_AX_108/WEB_d61e2a2ef05825acd9efabcf6ba99ab1"
    ]
  },
  "lowerPrice": 0,
  "qrUrlDetail": "https://qr.altered.gg/ALT_EOLECB_A_AX_108_R1",
  "isOwnerless": true,
  "reference": "ALT_EOLECB_A_AX_108_R1",
  "id": "01KH6E458HGZ79546RNTGA0TYF",
  "mainFaction": {
    "@id": "/factions/AX",
    "@type": "Faction",
    "reference": "AX",
    "color": "#8c432a",
    "id": "01GE7AC9XBG707G19F03A95TH1",
    "name": "Axiom"
  },
  "allImagePath": {
    "fr-fr": "https://altered-prod-eu.s3.amazonaws.com/Art/EOLECB/CARDS/ALT_EOLECB_A_AX_108/JPG/fr_FR/73b67f3dc7d9cf786599bf9f681c69e2.jpg",
    "en-us": "https://altered-prod-eu.s3.amazonaws.com/Art/EOLECB/CARDS/ALT_EOLECB_A_AX_108/JPG/en_US/afbddb8a33784fcfcbc2ab31448833a1.jpg",
    "it-it": "https://altered-prod-eu.s3.amazonaws.com/Art/EOLECB/CARDS/ALT_EOLECB_A_AX_108/JPG/it_IT/8dfd192510eae9f851e0af059db598a1.jpg",
    "es-es": "https://altered-prod-eu.s3.amazonaws.com/Art/EOLECB/CARDS/ALT_EOLECB_A_AX_108/JPG/es_ES/57a3f043c0a7b4e274049495f0388c1b.jpg",
    "de-de": "https://altered-prod-eu.s3.amazonaws.com/Art/EOLECB/CARDS/ALT_EOLECB_A_AX_108/JPG/de_DE/d33aba9dfed211c8a7c84ae80d178fbc.jpg"
  },
  "name": "Verderbter Paju",
  "elements": {
    "MAIN_COST": "2",
    "RECALL_COST": "2",
    "OCEAN_POWER": "#0#",
    "FOREST_POWER": "2",
    "MOUNTAIN_POWER": "2",
    "MAIN_EFFECT": "#Ich kann nicht gespielt werden,# falls eine andere Karte in deiner Hand ist.  #{J}# Erschaffe eine [Aerolit]-Marke in deinem Wahrzeichen-Bereich.",
    "ECHO_EFFECT": "#{D} : Erschaffe eine [Aerolit]-Marke im Wahrzeichen-Bereich eines Spielers deiner Wahl.#"
  },
  "isSuspended": false,
  "isErrated": false,
  "isBanned": false,
  "isSerialized": false,
  "isParentSerialized": false,
  "collectorNumber": "[Code non trouvé]-DE"
}