{
  "@context": "/contexts/Card",
  "@id": "/cards/ALT_FUGUE_A_AX_146_C",
  "@type": "Card",
  "loreEntries": [],
  "cardType": {
    "@id": "/card_types/01J1Q78N4S1E64PN4T7GB4T59F",
    "@type": "CardType",
    "reference": "LANDMARK_PERMANENT",
    "id": "01J1Q78N4S1E64PN4T7GB4T59F",
    "name": "Permanente hito"
  },
  "cardSubTypes": [
    {
      "@type": "CardSubType",
      "@id": "/.well-known/genid/df44a904772fa15ba780",
      "reference": "CONSTRUCTION",
      "id": "01J1SYC159ACKJS202498RAQRR",
      "name": "Construcción"
    }
  ],
  "cardSet": {
    "@id": "/card_sets/FUGUE",
    "@type": "CardSet",
    "id": "01KM5YCEK1YMWY30RHG5PV0MFY",
    "reference": "FUGUE",
    "name": "Neverending Journey"
  },
  "rarity": {
    "@type": "Rarity",
    "@id": "/.well-known/genid/034f4badd47485d3d501",
    "reference": "COMMON",
    "id": "01GE7AC9WEQKW1Y1BF8SCY745A",
    "name": "Common"
  },
  "imagePath": "https://altered-prod-eu.s3.amazonaws.com/Art/FUGUE/CARDS/ALT_FUGUE_A_AX_146/JPG/es_ES/65dcb47f4b245ee4e351193beda4c0e0.jpg",
  "assets": [],
  "lowerPrice": 0,
  "qrUrlDetail": "https://qr.altered.gg/ALT_FUGUE_A_AX_146_C",
  "isOwnerless": true,
  "reference": "ALT_FUGUE_A_AX_146_C",
  "id": "41ENXB7RPH9GPRW7S8QA0RX7PH",
  "mainFaction": {
    "@id": "/factions/AX",
    "@type": "Faction",
    "reference": "AX",
    "color": "#8c432a",
    "id": "01GE7AC9XBG707G19F03A95TH1",
    "name": "Axiom"
  },
  "allImagePath": {
    "fr-fr": "https://altered-prod-eu.s3.amazonaws.com/Art/FUGUE/CARDS/ALT_FUGUE_A_AX_146/JPG/fr_FR/6d046420866b6eaa89155494bf193c6c.jpg",
    "en-us": "https://altered-prod-eu.s3.amazonaws.com/Art/FUGUE/CARDS/ALT_FUGUE_A_AX_146/JPG/en_US/01e8b223342c42e76e585afa47bf4bfb.jpg",
    "it-it": "https://altered-prod-eu.s3.amazonaws.com/Art/FUGUE/CARDS/ALT_FUGUE_A_AX_146/JPG/it_IT/cbbcd6f924d25bda2157c2c00b1213de.jpg",
    "es-es": "https://altered-prod-eu.s3.amazonaws.com/Art/FUGUE/CARDS/ALT_FUGUE_A_AX_146/JPG/es_ES/65dcb47f4b245ee4e351193beda4c0e0.jpg",
    "de-de": "https://altered-prod-eu.s3.amazonaws.com/Art/FUGUE/CARDS/ALT_FUGUE_A_AX_146/JPG/de_DE/7a42db8b293fe47e525aef3058723801.jpg"
  },
  "name": "",
  "elements": {
    "MAIN_COST": "3",
    "RECALL_COST": "3",
    "OCEAN_POWER": "",
    "FOREST_POWER": "",
    "MOUNTAIN_POWER": "",
    "MAIN_EFFECT": "{J} [Sabotea].  At Noon — Target Character in your Reserve gains 1 boost."
  },
  "isSuspended": false,
  "isErrated": false,
  "isBanned": false,
  "isSerialized": false,
  "isParentSerialized": false,
  "collectorNumber": "NEJ-A-015-C-ES"
}