{
  "@context": "/contexts/Card",
  "@id": "/cards/ALT_DUSTER_B_LY_88_R2",
  "@type": "Card",
  "loreEntries": [
    {
      "@id": "/lore_entries/2FDP520YE88NY9MSRNQG1QW3Z7",
      "@type": "LoreEntry",
      "loreEntryElements": [
        {
          "@id": "/lore_entry_elements/01JZ37ZMPNHDHTQTBCK21DD3NQ",
          "@type": "LoreEntryElement",
          "loreEntryElementType": {
            "@id": "/lore_entry_element_types/01GR6AENPX6HQP8G16KNV7BNA2",
            "@type": "LoreEntryElementType",
            "id": "01GR6AENPX6HQP8G16KNV7BNA2",
            "reference": "FLAVOR_TEXT",
            "subject": "Flavor Text"
          },
          "id": "01JZ37ZMPNHDHTQTBCK21DD3NQ",
          "text": "La distanza più breve tra due punti è una linea retta."
        },
        {
          "@id": "/lore_entry_elements/01JZ37ZMQF15J2H6MKY9VMTF28",
          "@type": "LoreEntryElement",
          "loreEntryElementType": {
            "@id": "/lore_entry_element_types/01GR6AE2ZSVVYP6SDJXN8Q5DVF",
            "@type": "LoreEntryElementType",
            "id": "01GR6AE2ZSVVYP6SDJXN8Q5DVF",
            "reference": "STORY",
            "subject": "Story"
          },
          "id": "01JZ37ZMQF15J2H6MKY9VMTF28",
          "text": ""
        },
        {
          "@id": "/lore_entry_elements/01JZ37ZMQ3WJ66E8QPH0MXG4TK",
          "@type": "LoreEntryElement",
          "loreEntryElementType": {
            "@id": "/lore_entry_element_types/01GR6AFCC93PF6T4EYVTXXYJY9",
            "@type": "LoreEntryElementType",
            "id": "01GR6AFCC93PF6T4EYVTXXYJY9",
            "reference": "INSPIRATION",
            "subject": "Inspiration"
          },
          "id": "01JZ37ZMQ3WJ66E8QPH0MXG4TK",
          "text": ""
        },
        {
          "@id": "/lore_entry_elements/01JZ37ZMNCC3FESR7J7DZDGMFN",
          "@type": "LoreEntryElement",
          "loreEntryElementType": {
            "@id": "/lore_entry_element_types/01H19024M31D80P12EJCYX9GB0",
            "@type": "LoreEntryElementType",
            "id": "01H19024M31D80P12EJCYX9GB0",
            "reference": "NARRATOR",
            "subject": "Narrator"
          },
          "id": "01JZ37ZMNCC3FESR7J7DZDGMFN",
          "text": ""
        },
        {
          "@id": "/lore_entry_elements/01JZ37ZMNSHCYVS8DRC4HTMGFT",
          "@type": "LoreEntryElement",
          "loreEntryElementType": {
            "@id": "/lore_entry_element_types/01GS7V4ZMD4F2Q0EVQ2GSSJHE2",
            "@type": "LoreEntryElementType",
            "id": "01GS7V4ZMD4F2Q0EVQ2GSSJHE2",
            "reference": "DATE",
            "subject": "Date"
          },
          "id": "01JZ37ZMNSHCYVS8DRC4HTMGFT",
          "text": ""
        }
      ],
      "loreEntryType": {
        "@id": "/lore_entry_types/01HNGY4YPR0FVZVYWD8YFE0PHP",
        "@type": "LoreEntryType",
        "id": "01HNGY4YPR0FVZVYWD8YFE0PHP",
        "reference": "CHARACTER",
        "name": "Character"
      },
      "id": "2FDP520YE88NY9MSRNQG1QW3Z7",
      "reference": "ALT_DUSTER_B_LY_88_C"
    }
  ],
  "cardType": {
    "@id": "/card_types/01H19NWA92A4ERAC4ATMSZNASS",
    "@type": "CardType",
    "reference": "CHARACTER",
    "id": "01H19NWA92A4ERAC4ATMSZNASS",
    "name": "Personaggio"
  },
  "cardSubTypes": [
    {
      "@type": "CardSubType",
      "@id": "/.well-known/genid/da8332d09fe8e8924b9a",
      "reference": "ADVENTURER",
      "id": "01HKAGPC92CGHANVSRSC8R8ES6",
      "name": "Avventuriero"
    }
  ],
  "cardSet": {
    "@id": "/card_sets/DUSTER",
    "@type": "CardSet",
    "id": "01K56FXHFTGF3DQ8XE8Q8Y5JG8",
    "reference": "DUSTER",
    "name": "Semi di Unità"
  },
  "rarity": {
    "@type": "Rarity",
    "@id": "/.well-known/genid/f9ddb448cd078e89aa98",
    "reference": "RARE",
    "id": "01GE7AC9WY6PK56RADXXD6P1T5",
    "name": "Rare"
  },
  "imagePath": "https://altered-prod-eu.s3.amazonaws.com/Art/DUSTER/CARDS/ALT_DUSTER_B_LY_88/JPG/it_IT/64e813fc5c85a0a81a63e6a53b6dc524.jpg",
  "assets": {
    "WEB": [
      "https://altered-prod-eu.s3.amazonaws.com/Art/DUSTER/CARDS/ALT_DUSTER_B_LY_88/WEB_2b4d1466ea2173022efe3330427ff14e",
      "https://altered-prod-eu.s3.amazonaws.com/Art/DUSTER/CARDS/ALT_DUSTER_B_LY_88/WEB_e8c4143d6d19e0e0d93216bbde8311cd",
      "https://altered-prod-eu.s3.amazonaws.com/Art/DUSTER/CARDS/ALT_DUSTER_B_LY_88/WEB_fff73ade08339b4aaff93f5f09b14495"
    ]
  },
  "lowerPrice": 0,
  "qrUrlDetail": "https://qr.altered.gg/ALT_DUSTER_B_LY_88_R2",
  "isOwnerless": false,
  "reference": "ALT_DUSTER_B_LY_88_R2",
  "id": "01JYP9SVPTWRP6MSB5E1RSJWYX",
  "mainFaction": {
    "@id": "/factions/OR",
    "@type": "Faction",
    "reference": "OR",
    "color": "#0f6593",
    "id": "01GE7AC9X78DXSNKNB15KCF69X",
    "name": "Ordis"
  },
  "allImagePath": {
    "fr-fr": "https://altered-prod-eu.s3.amazonaws.com/Art/DUSTER/CARDS/ALT_DUSTER_B_LY_88/JPG/fr_FR/cf50796a43e4ebbe84db8c9155750960.jpg",
    "en-us": "https://altered-prod-eu.s3.amazonaws.com/Art/DUSTER/CARDS/ALT_DUSTER_B_LY_88/JPG/en_US/9723e76ac0c69cb8a1419660a6e05bf3.jpg",
    "it-it": "https://altered-prod-eu.s3.amazonaws.com/Art/DUSTER/CARDS/ALT_DUSTER_B_LY_88/JPG/it_IT/64e813fc5c85a0a81a63e6a53b6dc524.jpg",
    "es-es": "https://altered-prod-eu.s3.amazonaws.com/Art/DUSTER/CARDS/ALT_DUSTER_B_LY_88/JPG/es_ES/2602d1db0c39e4989d7c996ba56c0f01.jpg",
    "de-de": "https://altered-prod-eu.s3.amazonaws.com/Art/DUSTER/CARDS/ALT_DUSTER_B_LY_88/JPG/de_DE/d460d3defc0715bdc7dbd2c7b2f0b392.jpg"
  },
  "name": "Viaggiatrice dei Cavi Reka",
  "elements": {
    "MAIN_COST": "2",
    "RECALL_COST": "2",
    "OCEAN_POWER": "0",
    "FOREST_POWER": "#2#",
    "MOUNTAIN_POWER": "#2#",
    "MAIN_EFFECT": "#{H} Se sono in {O}, crea una pedina [Seme di Mana] nei tuoi fulcri.#"
  },
  "isSuspended": false,
  "isErrated": false,
  "isBanned": false,
  "isSerialized": false,
  "isParentSerialized": false,
  "collectorNumber": "SDU-040-F-IT"
}