{
  "@context": "/contexts/Card",
  "@id": "/cards/ALT_FUGUE_B_YZ_140_R1",
  "@type": "Card",
  "loreEntries": [
    {
      "@id": "/lore_entries/4DBXQ6WC7G91N9MB1WRNAEX51R",
      "@type": "LoreEntry",
      "loreEntryElements": [
        {
          "@id": "/lore_entry_elements/01KN46ABFBZWSD8ED52DX0W8HP",
          "@type": "LoreEntryElement",
          "loreEntryElementType": {
            "@id": "/lore_entry_element_types/01GR6AENPX6HQP8G16KNV7BNA2",
            "@type": "LoreEntryElementType",
            "id": "01GR6AENPX6HQP8G16KNV7BNA2",
            "reference": "FLAVOR_TEXT",
            "subject": "Flavor Text"
          },
          "id": "01KN46ABFBZWSD8ED52DX0W8HP",
          "text": ""
        },
        {
          "@id": "/lore_entry_elements/01KN46ABG84DWT1PR1KYGBQW7A",
          "@type": "LoreEntryElement",
          "loreEntryElementType": {
            "@id": "/lore_entry_element_types/01GR6AE2ZSVVYP6SDJXN8Q5DVF",
            "@type": "LoreEntryElementType",
            "id": "01GR6AE2ZSVVYP6SDJXN8Q5DVF",
            "reference": "STORY",
            "subject": "Histoire"
          },
          "id": "01KN46ABG84DWT1PR1KYGBQW7A",
          "text": ""
        },
        {
          "@id": "/lore_entry_elements/01KN46ABFTN699WEJHGWNFEMJ5",
          "@type": "LoreEntryElement",
          "loreEntryElementType": {
            "@id": "/lore_entry_element_types/01GR6AFCC93PF6T4EYVTXXYJY9",
            "@type": "LoreEntryElementType",
            "id": "01GR6AFCC93PF6T4EYVTXXYJY9",
            "reference": "INSPIRATION",
            "subject": "Inspiration"
          },
          "id": "01KN46ABFTN699WEJHGWNFEMJ5",
          "text": ""
        },
        {
          "@id": "/lore_entry_elements/01KN46ABDDAJJ62FQZ3V6FAFAP",
          "@type": "LoreEntryElement",
          "loreEntryElementType": {
            "@id": "/lore_entry_element_types/01H19024M31D80P12EJCYX9GB0",
            "@type": "LoreEntryElementType",
            "id": "01H19024M31D80P12EJCYX9GB0",
            "reference": "NARRATOR",
            "subject": "Narré par"
          },
          "id": "01KN46ABDDAJJ62FQZ3V6FAFAP",
          "text": ""
        },
        {
          "@id": "/lore_entry_elements/01KN46ABDSRJV7H68QZ18BK7ZT",
          "@type": "LoreEntryElement",
          "loreEntryElementType": {
            "@id": "/lore_entry_element_types/01GS7V4ZMD4F2Q0EVQ2GSSJHE2",
            "@type": "LoreEntryElementType",
            "id": "01GS7V4ZMD4F2Q0EVQ2GSSJHE2",
            "reference": "DATE",
            "subject": "Date"
          },
          "id": "01KN46ABDSRJV7H68QZ18BK7ZT",
          "text": ""
        }
      ],
      "loreEntryType": {
        "@id": "/lore_entry_types/01HNGY4YPR0FVZVYWD8YFE0PHP",
        "@type": "LoreEntryType",
        "id": "01HNGY4YPR0FVZVYWD8YFE0PHP",
        "reference": "CHARACTER",
        "name": "Character"
      },
      "id": "4DBXQ6WC7G91N9MB1WRNAEX51R",
      "reference": "ALT_FUGUE_B_YZ_140_C"
    }
  ],
  "cardType": {
    "@id": "/card_types/01H19NWA92A4ERAC4ATMSZNASS",
    "@type": "CardType",
    "reference": "CHARACTER",
    "id": "01H19NWA92A4ERAC4ATMSZNASS",
    "name": "Personnage"
  },
  "cardSubTypes": [
    {
      "@type": "CardSubType",
      "@id": "/.well-known/genid/be071be0fe95e44782ff",
      "reference": "FAIRY",
      "id": "01HKAGPBKC6V2RK28EZGHP8VWW",
      "name": "Fée"
    }
  ],
  "cardSet": {
    "@id": "/card_sets/FUGUE",
    "@type": "CardSet",
    "id": "01KM5YCEK1YMWY30RHG5PV0MFY",
    "reference": "FUGUE",
    "name": "La Traversée Éternelle"
  },
  "rarity": {
    "@type": "Rarity",
    "@id": "/.well-known/genid/a09c8f5a51651bc7e2f5",
    "reference": "RARE",
    "id": "01GE7AC9WY6PK56RADXXD6P1T5",
    "name": "Rare"
  },
  "imagePath": "https://altered-prod-eu.s3.amazonaws.com/Art/FUGUE/CARDS/ALT_FUGUE_B_YZ_140/JPG/fr_FR/7b9c314b3e395aa57ec5273b05214b53.jpg",
  "assets": {
    "WEB": [
      "https://altered-prod-eu.s3.amazonaws.com/Art/FUGUE/CARDS/ALT_FUGUE_B_YZ_140/WEB_f4d42d5fb55c6faca8ae286074d57ba2",
      "https://altered-prod-eu.s3.amazonaws.com/Art/FUGUE/CARDS/ALT_FUGUE_B_YZ_140/WEB_e169ca4f493885493b44039518d12bfd",
      "https://altered-prod-eu.s3.amazonaws.com/Art/FUGUE/CARDS/ALT_FUGUE_B_YZ_140/WEB_eba77efc9e191bbbbfcac421d7516783"
    ]
  },
  "lowerPrice": 0,
  "qrUrlDetail": "https://qr.altered.gg/ALT_FUGUE_B_YZ_140_R1",
  "isOwnerless": true,
  "reference": "ALT_FUGUE_B_YZ_140_R1",
  "id": "1S8YA50X7W8P6AYEHG3FWPNBP0",
  "mainFaction": {
    "@id": "/factions/YZ",
    "@type": "Faction",
    "reference": "YZ",
    "color": "#764891",
    "id": "01GE7AC9WEQKW1Y1BF8SCY7459",
    "name": "Yzmir"
  },
  "allImagePath": {
    "fr-fr": "https://altered-prod-eu.s3.amazonaws.com/Art/FUGUE/CARDS/ALT_FUGUE_B_YZ_140/JPG/fr_FR/7b9c314b3e395aa57ec5273b05214b53.jpg",
    "en-us": "https://altered-prod-eu.s3.amazonaws.com/Art/FUGUE/CARDS/ALT_FUGUE_B_YZ_140/JPG/en_US/c82b12bc1f6996e06995768ef325b918.jpg",
    "it-it": "https://altered-prod-eu.s3.amazonaws.com/Art/FUGUE/CARDS/ALT_FUGUE_B_YZ_140/JPG/it_IT/80db49ebe70fb8740c72884d697cc506.jpg",
    "es-es": "https://altered-prod-eu.s3.amazonaws.com/Art/FUGUE/CARDS/ALT_FUGUE_B_YZ_140/JPG/es_ES/87013fd5c9a1760cd495c16c45534569.jpg",
    "de-de": "https://altered-prod-eu.s3.amazonaws.com/Art/FUGUE/CARDS/ALT_FUGUE_B_YZ_140/JPG/de_DE/53007770e9cc20a9a05ea04c72862f3e.jpg"
  },
  "name": "Sirène",
  "elements": {
    "MAIN_COST": "#5#",
    "RECALL_COST": "1",
    "OCEAN_POWER": "2",
    "FOREST_POWER": "1",
    "MOUNTAIN_POWER": "1",
    "MAIN_EFFECT": "{H} Un Personnage non-[[Ancré]] #de Coût de Base {3} ou moins# trahit."
  },
  "isSuspended": false,
  "isErrated": false,
  "isBanned": false,
  "isSerialized": false,
  "isParentSerialized": false,
  "collectorNumber": "NEJ-101-R-FR"
}