{
  "@context": "/contexts/Card",
  "@id": "/cards/ALT_FUGUE_B_OR_140_R2",
  "@type": "Card",
  "loreEntries": [
    {
      "@id": "/lore_entries/1JV9T9V19Q80BT6V55C9SB5ACY",
      "@type": "LoreEntry",
      "loreEntryElements": [
        {
          "@id": "/lore_entry_elements/01KN46A9BD7ZRPM1CCCS750WFY",
          "@type": "LoreEntryElement",
          "loreEntryElementType": {
            "@id": "/lore_entry_element_types/01GR6AENPX6HQP8G16KNV7BNA2",
            "@type": "LoreEntryElementType",
            "id": "01GR6AENPX6HQP8G16KNV7BNA2",
            "reference": "FLAVOR_TEXT",
            "subject": "Flavor Text"
          },
          "id": "01KN46A9BD7ZRPM1CCCS750WFY",
          "text": "Dix ans de guerre, au nom de la beauté d’une seule."
        },
        {
          "@id": "/lore_entry_elements/01KN46A9C1704NH1E27T77Z9W8",
          "@type": "LoreEntryElement",
          "loreEntryElementType": {
            "@id": "/lore_entry_element_types/01GR6AE2ZSVVYP6SDJXN8Q5DVF",
            "@type": "LoreEntryElementType",
            "id": "01GR6AE2ZSVVYP6SDJXN8Q5DVF",
            "reference": "STORY",
            "subject": "Histoire"
          },
          "id": "01KN46A9C1704NH1E27T77Z9W8",
          "text": ""
        },
        {
          "@id": "/lore_entry_elements/01KN46A9BQVMHSY1P206EK8BTS",
          "@type": "LoreEntryElement",
          "loreEntryElementType": {
            "@id": "/lore_entry_element_types/01GR6AFCC93PF6T4EYVTXXYJY9",
            "@type": "LoreEntryElementType",
            "id": "01GR6AFCC93PF6T4EYVTXXYJY9",
            "reference": "INSPIRATION",
            "subject": "Inspiration"
          },
          "id": "01KN46A9BQVMHSY1P206EK8BTS",
          "text": ""
        },
        {
          "@id": "/lore_entry_elements/01KN46A9AQ6QRGWRSRTT73501Z",
          "@type": "LoreEntryElement",
          "loreEntryElementType": {
            "@id": "/lore_entry_element_types/01H19024M31D80P12EJCYX9GB0",
            "@type": "LoreEntryElementType",
            "id": "01H19024M31D80P12EJCYX9GB0",
            "reference": "NARRATOR",
            "subject": "Narré par"
          },
          "id": "01KN46A9AQ6QRGWRSRTT73501Z",
          "text": ""
        },
        {
          "@id": "/lore_entry_elements/01KN46A9B3QK3H0CR014YKZ82R",
          "@type": "LoreEntryElement",
          "loreEntryElementType": {
            "@id": "/lore_entry_element_types/01GS7V4ZMD4F2Q0EVQ2GSSJHE2",
            "@type": "LoreEntryElementType",
            "id": "01GS7V4ZMD4F2Q0EVQ2GSSJHE2",
            "reference": "DATE",
            "subject": "Date"
          },
          "id": "01KN46A9B3QK3H0CR014YKZ82R",
          "text": ""
        }
      ],
      "loreEntryType": {
        "@id": "/lore_entry_types/01HNGY4YPR0FVZVYWD8YFE0PHP",
        "@type": "LoreEntryType",
        "id": "01HNGY4YPR0FVZVYWD8YFE0PHP",
        "reference": "CHARACTER",
        "name": "Character"
      },
      "id": "1JV9T9V19Q80BT6V55C9SB5ACY",
      "reference": "ALT_FUGUE_B_OR_140_C"
    }
  ],
  "cardType": {
    "@id": "/card_types/01H19NWA92A4ERAC4ATMSZNASS",
    "@type": "CardType",
    "reference": "CHARACTER",
    "id": "01H19NWA92A4ERAC4ATMSZNASS",
    "name": "Personnage"
  },
  "cardSubTypes": [
    {
      "@type": "CardSubType",
      "@id": "/.well-known/genid/98fa0417d01ef29a808e",
      "reference": "CITIZEN",
      "id": "01HKAGQWDFDGS8YVZGW98BVV9D",
      "name": "Citoyen"
    },
    {
      "@type": "CardSubType",
      "@id": "/.well-known/genid/7eabb6171def71a5c15a",
      "reference": "NOBLE",
      "id": "01HKAGVEV163KJH0BWMZ6WR7E9",
      "name": "Noble"
    }
  ],
  "cardSet": {
    "@id": "/card_sets/FUGUE",
    "@type": "CardSet",
    "id": "01KM5YCEK1YMWY30RHG5PV0MFY",
    "reference": "FUGUE",
    "name": "La Traversée Éternelle"
  },
  "rarity": {
    "@type": "Rarity",
    "@id": "/.well-known/genid/3d22c5f2521cf4ccd75f",
    "reference": "RARE",
    "id": "01GE7AC9WY6PK56RADXXD6P1T5",
    "name": "Rare"
  },
  "imagePath": "https://altered-prod-eu.s3.amazonaws.com/Art/FUGUE/CARDS/ALT_FUGUE_B_OR_140/JPG/fr_FR/ecb12dd472dee8caff4141923aa66497.jpg",
  "assets": {
    "WEB": [
      "https://altered-prod-eu.s3.amazonaws.com/Art/FUGUE/CARDS/ALT_FUGUE_B_OR_140/WEB_6ce6713df73c93ffb2f5b519d0b95e17",
      "https://altered-prod-eu.s3.amazonaws.com/Art/FUGUE/CARDS/ALT_FUGUE_B_OR_140/WEB_111f0648db8f2f83fa8d0b218a92e665",
      "https://altered-prod-eu.s3.amazonaws.com/Art/FUGUE/CARDS/ALT_FUGUE_B_OR_140/WEB_fe2707740e3e01abc495bed1c64e9c64"
    ]
  },
  "lowerPrice": 0,
  "qrUrlDetail": "https://qr.altered.gg/ALT_FUGUE_B_OR_140_R2",
  "isOwnerless": true,
  "reference": "ALT_FUGUE_B_OR_140_R2",
  "id": "2PGWJHN2DS9D6TNFF53DY8475B",
  "mainFaction": {
    "@id": "/factions/YZ",
    "@type": "Faction",
    "reference": "YZ",
    "color": "#764891",
    "id": "01GE7AC9WEQKW1Y1BF8SCY7459",
    "name": "Yzmir"
  },
  "allImagePath": {
    "fr-fr": "https://altered-prod-eu.s3.amazonaws.com/Art/FUGUE/CARDS/ALT_FUGUE_B_OR_140/JPG/fr_FR/ecb12dd472dee8caff4141923aa66497.jpg",
    "en-us": "https://altered-prod-eu.s3.amazonaws.com/Art/FUGUE/CARDS/ALT_FUGUE_B_OR_140/JPG/en_US/eec199384f033323e44dd267a5c261e7.jpg",
    "it-it": "https://altered-prod-eu.s3.amazonaws.com/Art/FUGUE/CARDS/ALT_FUGUE_B_OR_140/JPG/it_IT/c955e63ddd4a5704c879fc70f30c0472.jpg",
    "es-es": "https://altered-prod-eu.s3.amazonaws.com/Art/FUGUE/CARDS/ALT_FUGUE_B_OR_140/JPG/es_ES/306c56fb8112f4dc37aa1c17c61ee055.jpg",
    "de-de": "https://altered-prod-eu.s3.amazonaws.com/Art/FUGUE/CARDS/ALT_FUGUE_B_OR_140/JPG/de_DE/f373124c5168780d433ed6068a904639.jpg"
  },
  "name": "Hélène de Troie",
  "elements": {
    "MAIN_COST": "3",
    "RECALL_COST": "#1#",
    "OCEAN_POWER": "1",
    "FOREST_POWER": "1",
    "MOUNTAIN_POWER": "#2#",
    "MAIN_EFFECT": "#{H}# Créez un jeton Soldat [1/1/1 Recrue Ordis] dans chacune de vos Expéditions."
  },
  "isSuspended": false,
  "isErrated": false,
  "isBanned": false,
  "isSerialized": false,
  "isParentSerialized": false,
  "collectorNumber": "NEJ-083-F-FR"
}