{
  "@context": "/contexts/PublicCard",
  "@id": "/public/cards/ALT_EOLEOP_P_YZ_112_C",
  "@type": "PublicCard",
  "id": "01KGH7QTMT2NQDYEP7RX0FHY5V",
  "reference": "ALT_EOLEOP_P_YZ_112_C",
  "cardType": {
    "@type": "CardTypeDTO",
    "@id": "/.well-known/genid/a38d4021f216ab16ce91",
    "id": "01H19NWA92A4ERAC4ATMSZNASS",
    "reference": "CHARACTER",
    "name": "Personnage",
    "sequence": 3
  },
  "cardSet": {
    "@type": "CardSetDTO",
    "@id": "/.well-known/genid/3b17b3dd14d1fbb8a88f",
    "id": "01KGH7QT3S6RRZK2S0BNBVNH3K",
    "reference": "EOLEOP",
    "name": "Les Racines de la Corruption - Jeu Organisé",
    "description": null,
    "code": "ROCOP",
    "isActive": true,
    "isReward": true
  },
  "cardSubTypes": [
    {
      "@type": "CardSubTypeDTO",
      "@id": "/.well-known/genid/aa6736e59a18be632d30",
      "id": "01HKAGXDF5A4KJW7GVC25YQS3H",
      "reference": "MAGE",
      "name": "Mage"
    }
  ],
  "elements": {
    "MAIN_COST": "2",
    "RECALL_COST": "2",
    "MOUNTAIN_POWER": "2",
    "OCEAN_POWER": "2",
    "FOREST_POWER": "2",
    "MAIN_EFFECT": "{H} Défaussez la première carte de votre deck.",
    "ECHO_EFFECT": ""
  },
  "rarity": {
    "@type": "RarityDTO",
    "@id": "/.well-known/genid/d6ac42152d2582311de4",
    "id": "01GE7AC9WEQKW1Y1BF8SCY745A",
    "reference": "COMMON",
    "name": "Commun",
    "sequence": 0
  },
  "imagePath": "https://altered-prod-eu.s3.amazonaws.com/Art/EOLEOP/CARDS/ALT_EOLEOP_P_YZ_112/JPG/fr_FR/150a56f9029e6f0c9b98896e2254971f.jpg",
  "assets": {
    "WEB": [
      "https://altered-prod-eu.s3.amazonaws.com/Art/EOLEOP/CARDS/ALT_EOLEOP_P_YZ_112/WEB_7e10be39098962bacfadebf39ba5473a",
      "https://altered-prod-eu.s3.amazonaws.com/Art/EOLEOP/CARDS/ALT_EOLEOP_P_YZ_112/WEB_fc0a838f539ad4d88430a65cffe182d9",
      "https://altered-prod-eu.s3.amazonaws.com/Art/EOLEOP/CARDS/ALT_EOLEOP_P_YZ_112/WEB_51c4e3e7151511ff33b2b3d0a1d07852"
    ]
  },
  "mainFaction": {
    "@type": "FactionDTO",
    "@id": "/.well-known/genid/3b03e885cf39d2e8e3bd",
    "id": "01GE7AC9WEQKW1Y1BF8SCY7459",
    "reference": "YZ",
    "name": "Yzmir",
    "color": "#764891"
  },
  "name": "Exorciste du Qorgan",
  "isSuspended": false,
  "isSerialized": false,
  "isParentSerialized": false,
  "isErrated": false,
  "isBanned": false,
  "isOwnerless": false,
  "inSale": 0,
  "lowerPrice": 0,
  "lowerOfferId": "",
  "isExclusive": true,
  "collectorNumber": "ALT_EOLEOP_P_YZ_112_C-FR"
}